loggoblin/__init__.py
loggoblin/__main__.py
loggoblin/cli.py
loggoblin-1.0.dist-info/LICENSE
loggoblin-1.0.dist-info/METADATA
loggoblin-1.0.dist-info/WHEEL
loggoblin-1.0.dist-info/entry_points.txt
loggoblin-1.0.dist-info/top_level.txt
loggoblin-1.0.dist-info/RECORD
